ODIContracts/__init__.py
ODIContracts/access/__init__.py
ODIContracts/access/roles.py
ODIContracts/access/role/BurnerRole.py
ODIContracts/access/role/MinterRole.py
ODIContracts/access/role/PauserRole.py
ODIContracts/access/role/__init__.py
ODIContracts/tokens/IIRC2.py
ODIContracts/tokens/IRC2.py
ODIContracts/tokens/IRC2burnable.py
ODIContracts/tokens/IRC2capped.py
ODIContracts/tokens/IRC2mintable.py
ODIContracts/tokens/IRC2pausable.py
ODIContracts/tokens/IRC2snapshot.py
ODIContracts/tokens/__init__.py
ODIContracts/utils/__init__.py
ODIContracts/utils/checks.py
ODIContracts/utils/consts.py
ODIContracts/utils/pausable.py
odi_token_contracts-0.0.5.dist-info/METADATA
odi_token_contracts-0.0.5.dist-info/WHEEL
odi_token_contracts-0.0.5.dist-info/top_level.txt
odi_token_contracts-0.0.5.dist-info/RECORD
