Metadata-Version: 2.1
Name: odi-token-contracts
Version: 0.0.5
Summary: Implementation of Mintable, Burnable, Capped, Pausable and Snapshot IRC2 token that can be used as standard token equivalent to ERC20 for ICON blockchain.
Home-page: https://github.com/OpenDevICON/odi-contracts/
Author: Prajwol Gyawali
Author-email: mail.prajwolgyawali@gmail.com
License: UNKNOWN
Platform: UNKNOWN
Classifier: Programming Language :: Python :: 3
Classifier: License :: OSI Approved :: MIT License
Classifier: Operating System :: OS Independent
Requires-Python: >=3.6
